hwc_bgr_888_image_to_base64_uri.py
hwc_bgr_888_image_to_base64_uri-0.1.0a0.dist-info/licenses/LICENSE
hwc_bgr_888_image_to_base64_uri-0.1.0a0.dist-info/METADATA
hwc_bgr_888_image_to_base64_uri-0.1.0a0.dist-info/WHEEL
hwc_bgr_888_image_to_base64_uri-0.1.0a0.dist-info/top_level.txt
hwc_bgr_888_image_to_base64_uri-0.1.0a0.dist-info/RECORD
