Metadata-Version: 2.4
Name: hwc-bgr-888-image-to-base64-uri
Version: 0.1.0a0
Summary: A specialized utility for converting OpenCV-compatible HWC BGR 888 images to Base64-encoded data URIs. Can be used with the OpenAI Chat Completions API.
Author-email: Jifeng Wu <jifengwu2k@gmail.com>
License-Expression: MIT
Project-URL: Homepage, https://github.com/jifengwu2k/hwc-bgr-888-image-to-base64-uri
Project-URL: Bug Tracker, https://github.com/jifengwu2k/hwc-bgr-888-image-to-base64-uri/issues
Classifier: Programming Language :: Python :: 2
Classifier: Programming Language :: Python :: 3
Classifier: Operating System :: OS Independent
Requires-Python: >=2
License-File: LICENSE
Requires-Dist: numpy
Requires-Dist: opencv-python
Dynamic: license-file
